arkhotool/__init__.py
arkhotool/error_handler.py
arkhotools-0.0.1.dist-info/LICENSE.txt
arkhotools-0.0.1.dist-info/METADATA
arkhotools-0.0.1.dist-info/WHEEL
arkhotools-0.0.1.dist-info/top_level.txt
arkhotools-0.0.1.dist-info/RECORD
