Metadata-Version: 2.1
Name: arkhotools
Version: 0.0.1
Summary: Set de herramientas para desarrollo en lamdba python AWS
Home-page: https://gitlab.com/arkhotech/arkholabs/lambda-tools.git
Author: Marcelo Silva
Author-email: msilva@arkho.tech
License: UNKNOWN
Platform: UNKNOWN
Classifier: Programming Language :: Python :: 3
Classifier: License :: OSI Approved :: MIT License
Classifier: Operating System :: OS Independent
Requires-Python: >=3.6
